esp_coredump/__init__.py
esp_coredump/cli_ext.py
esp_coredump/coredump.py
esp_coredump/tools.py
esp_coredump/corefile/__init__.py
esp_coredump/corefile/_parse_soc_header.py
esp_coredump/corefile/elf.py
esp_coredump/corefile/gdb.py
esp_coredump/corefile/loader.py
esp_coredump/corefile/riscv.py
esp_coredump/corefile/xtensa.py
esp_coredump/corefile/soc_headers/__init__.py
esp_coredump/corefile/soc_headers/esp32.py
esp_coredump/corefile/soc_headers/esp32c2.py
esp_coredump/corefile/soc_headers/esp32c3.py
esp_coredump/corefile/soc_headers/esp32c5.py
esp_coredump/corefile/soc_headers/esp32c6.py
esp_coredump/corefile/soc_headers/esp32c61.py
esp_coredump/corefile/soc_headers/esp32h2.py
esp_coredump/corefile/soc_headers/esp32p4.py
esp_coredump/corefile/soc_headers/esp32s2.py
esp_coredump/corefile/soc_headers/esp32s3.py
esp_coredump/scripts/__init__.py
esp_coredump/scripts/espcoredump.py
esp_coredump/scripts/run_tests.py
tests/__init__.py
tests/test_espcoredump.py
esp_coredump-1.12.0.dist-info/LICENSE
esp_coredump-1.12.0.dist-info/METADATA
esp_coredump-1.12.0.dist-info/WHEEL
esp_coredump-1.12.0.dist-info/entry_points.txt
esp_coredump-1.12.0.dist-info/top_level.txt
esp_coredump-1.12.0.dist-info/RECORD
