Metadata-Version: 2.1
Name: esp-coredump
Version: 1.12.0
Summary: Generate core dumps on unrecoverable software errors
Author: Espressif Systems
License: Apache License
Project-URL: Homepage, https://github.com/espressif/esp-coredump
Classifier: Development Status :: 5 - Production/Stable
Classifier: Intended Audience :: Developers
Classifier: Natural Language :: English
Classifier: Environment :: Console
Classifier: Topic :: Software Development :: Embedded Systems
Classifier: Programming Language :: Python :: 3 :: Only
Classifier: Programming Language :: Python :: 3.7
Classifier: Programming Language :: Python :: 3.8
Classifier: Programming Language :: Python :: 3.9
Classifier: Programming Language :: Python :: 3.10
Classifier: Programming Language :: Python :: 3.11
Classifier: Programming Language :: Python :: 3.12
Classifier: Operating System :: OS Independent
Classifier: License :: OSI Approved :: Apache Software License
Requires-Python: >=3.7
License-File: LICENSE
Requires-Dist: construct ~=2.10
Requires-Dist: pygdbmi >=0.9.0.2
Requires-Dist: esptool
Provides-Extra: dev
Requires-Dist: pre-commit ; extra == 'dev'
Requires-Dist: commitizen ; extra == 'dev'
Provides-Extra: test
Requires-Dist: coverage[toml] ; extra == 'test'
